knopfler.py
knopfler-0.2.2.dist-info/METADATA
knopfler-0.2.2.dist-info/WHEEL
knopfler-0.2.2.dist-info/entry_points.txt
knopfler-0.2.2.dist-info/top_level.txt
knopfler-0.2.2.dist-info/RECORD
