Metadata-Version: 2.4
Name: knopfler
Version: 0.2.2
Requires-Python: >=3.10
Requires-Dist: fastapi>=0.115.12
Requires-Dist: uvicorn>=0.34.2
Provides-Extra: matrix
Requires-Dist: matrix-client>=0.4.0; extra == "matrix"
Provides-Extra: rocketchat
Requires-Dist: rocketchatapibot>=0.1.4; extra == "rocketchat"
